{
  "schemaVersion": 1,
  "id": "9ed2a17f-9614-47f6-92bd-d22b644be283",
  "target": "articles/investigacao-apos-perdas-recorrentes",
  "generatedAt": "2026-06-08T13:21:16.716Z",
  "updatedAt": "2026-06-08T13:21:16.716Z",
  "contentHash": "bd54383a8e477681b9d78af4d0c7dba28f578ffded1323f02ffb035d43f5630b",
  "contentStatus": "draft",
  "riskDomains": [
    "clinical",
    "psychological"
  ],
  "decision": "needs_changes",
  "publicationAllowed": false,
  "summary": "1 apontamento(s) exigem decisão.",
  "agents": {
    "research": "pending_assisted_execution",
    "challenge": "needs_changes",
    "editorial": "suggestions_available",
    "aiApproval": "needs_changes",
    "publication": "blocked_until_human_gates"
  },
  "findings": [
    {
      "id": "32d4f45c4f4f3975",
      "domain": "editorial",
      "severity": "medium",
      "exactText": "Pendência humana",
      "occurrence": 1,
      "line": 47,
      "rationale": "O texto declara uma pendência humana que precisa ser confirmada antes da publicação.",
      "suggestedReplacement": "Pendência humana",
      "relatedSources": [],
      "resolution": {
        "status": "pending",
        "replacement": "",
        "justification": ""
      }
    }
  ],
  "history": [
    {
      "occurredAt": "2026-06-08T13:21:16.716Z",
      "action": "review_generated",
      "actor": "editorial-pipeline"
    }
  ]
}
